LivePeerSDK_Python/LivePeerSDK.py
LivePeerSDK_Python/__init__.py
LivePeerSDK-1.0.dist-info/LICENSE.txt
LivePeerSDK-1.0.dist-info/METADATA
LivePeerSDK-1.0.dist-info/WHEEL
LivePeerSDK-1.0.dist-info/top_level.txt
LivePeerSDK-1.0.dist-info/RECORD
