Metadata-Version: 2.1
Name: LivePeerSDK
Version: 1.0
Summary: A simple comprehensive Python Wrapper for LivePeerAPI.
Home-page: https://pypi.org/project/LivePeerSDK/
Author: Ragavendiran Balasubramanian
Author-email: bgragavendiran@gmail.com
License: MIT
Project-URL: Git Link, https://github.com/RAGANITHI/EthernalHacks-LivePeerSDK
Keywords: LivePeerSDK
Platform: UNKNOWN
Classifier: Programming Language :: Python :: 3
Classifier: License :: OSI Approved :: MIT License
Classifier: Operating System :: OS Independent
Requires-Python: >=3
License-File: LICENSE.txt
Requires-Dist: requests
